{
  "propertyId": 5773535,
  "name": "My Home Aceh",
  "favoriteFeatures": [
    "Air conditioning",
    "Dry cleaning",
    "Restaurants",
    "Concierge",
    "Massage"
  ],
  "reviews": [
    {
      "hotelReviewId": 1050069461,
      "rating": 10.0,
      "ratingText": "Exceptional",
      "reviewDate": "2025-11-11T10:27:00+07:00",
      "reviewTitle": "Exceptional",
      "originalTitle": "",
      "originalComment": "Harga terjangkau dengan fasilitas yg msh terjaga..sangat rekomendasi utk kamu yg mau menginap dgn hrg yg variatif dan fasilitas yg baik",
      "reviewComments": "Affordable prices with well-maintained facilities... highly recommended for those who want to stay at varied prices and with good amenities.",
      "reviewPositives": "",
      "reviewNegatives": "",
      "reviewerCountry": "Indonesia",
      "reviewGroupName": "Solo traveler",
      "roomTypeName": "Apartment",
      "lengthOfStay": 1
    },
    {
      "hotelReviewId": 917162476,
      "rating": 7.0,
      "ratingText": "Very good",
      "reviewDate": "2025-01-08T00:00:00+07:00",
      "reviewTitle": "Very good",
      "originalTitle": "",
      "originalComment": "",
      "reviewComments": "",
      "reviewPositives": "Though the room is small but it's clean and well designed.",
      "reviewNegatives": "",
      "reviewerCountry": "",
      "reviewGroupName": "Family with young children",
      "roomTypeName": "",
      "lengthOfStay": 0
    },
    {
      "hotelReviewId": 848404666,
      "rating": 10.0,
      "ratingText": "Exceptional",
      "reviewDate": "2024-08-29T01:54:00+07:00",
      "reviewTitle": "Good Value ",
      "originalTitle": "",
      "originalComment": "",
      "reviewComments": "I stayed here one night as I was catching the 1st ferry to Pulau Weh.\nThe staff are friendly and helpful.\nMy room was spacious with hot running water in the bathroom.\nIn the lobby and on all floors theirs drinking water.\nMy Home is located close to local setting places that are amazing value for money.\nThe homestay is quiet with  no traffic noise and it's clean. There is a mosque close by. The call to prayer in the morning only lasts 10 - 15 minutes. Had I not been awake I would not have heard it.\nI would stay here again.\nRemember you are in Indonesia. It is basic.",
      "reviewPositives": "",
      "reviewNegatives": "",
      "reviewerCountry": "United Kingdom",
      "reviewGroupName": "Solo traveler",
      "roomTypeName": "Apartment",
      "lengthOfStay": 1
    },
    {
      "hotelReviewId": 819659396,
      "rating": 8.0,
      "ratingText": "Excellent",
      "reviewDate": "2024-06-01T00:00:00+07:00",
      "reviewTitle": "Great Location & Great Service",
      "originalTitle": "",
      "originalComment": "",
      "reviewComments": "",
      "reviewPositives": "This is my 2nd time staying here. I prefer this place is mainly due to the location & accessibility to nearby eateries and shops",
      "reviewNegatives": "",
      "reviewerCountry": "",
      "reviewGroupName": "Group",
      "roomTypeName": "",
      "lengthOfStay": 0
    },
    {
      "hotelReviewId": 1123203686,
      "rating": 7.2,
      "ratingText": "Very good",
      "reviewDate": "2026-05-24T12:33:00+07:00",
      "reviewTitle": "Very good",
      "originalTitle": "",
      "originalComment": "",
      "reviewComments": "The first room I was given had very poor WiFi reception. But I was able to change to another one with was much better. Both rooms are on the second floor.\nThere is cold and relatively hot water dispenser on every floor.",
      "reviewPositives": "",
      "reviewNegatives": "",
      "reviewerCountry": "Hong Kong SAR, China",
      "reviewGroupName": "Solo traveler",
      "roomTypeName": "Apartment",
      "lengthOfStay": 2
    },
    {
      "hotelReviewId": 768543936,
      "rating": 5.0,
      "ratingText": "Review score",
      "reviewDate": "2024-01-20T10:21:51+07:00",
      "reviewTitle": "Unless you’re extremely broke don’t stay here spend a little extra and get a nicer place.",
      "originalTitle": "",
      "originalComment": "",
      "reviewComments": "",
      "reviewPositives": "The room was clean I guess",
      "reviewNegatives": "Very small, extremely basic, they said there was Internet but none of us could connect which was disappointing.",
      "reviewerCountry": "",
      "reviewGroupName": "Couple",
      "roomTypeName": "",
      "lengthOfStay": 0
    },
    {
      "hotelReviewId": 841476311,
      "rating": 10.0,
      "ratingText": "Exceptional",
      "reviewDate": "2024-07-31T12:56:00+07:00",
      "reviewTitle": "Best budget location to stay in Banda Aceh",
      "originalTitle": "",
      "originalComment": "",
      "reviewComments": "Located in a small complex near the city center. For the price, it’s considered very decent. Worth the stay",
      "reviewPositives": "",
      "reviewNegatives": "",
      "reviewerCountry": "Indonesia",
      "reviewGroupName": "Solo traveler",
      "roomTypeName": "Apartment",
      "lengthOfStay": 8
    },
    {
      "hotelReviewId": 735502570,
      "rating": 8.0,
      "ratingText": "Excellent",
      "reviewDate": "2023-11-03T00:00:00+07:00",
      "reviewTitle": "i will stay here in future",
      "originalTitle": "",
      "originalComment": "",
      "reviewComments": "",
      "reviewPositives": "room big and clean",
      "reviewNegatives": "nothing",
      "reviewerCountry": "",
      "reviewGroupName": "Group",
      "roomTypeName": "",
      "lengthOfStay": 0
    },
    {
      "hotelReviewId": 965161666,
      "rating": 8.0,
      "ratingText": "Excellent",
      "reviewDate": "2025-05-17T09:04:00+07:00",
      "reviewTitle": "MyHome Hotel",
      "originalTitle": "",
      "originalComment": "",
      "reviewComments": "Recommended to stay in Acheh for location assesible to nearest food & souvenir facilities ",
      "reviewPositives": "",
      "reviewNegatives": "",
      "reviewerCountry": "Malaysia",
      "reviewGroupName": "Couple",
      "roomTypeName": "Apartment",
      "lengthOfStay": 2
    },
    {
      "hotelReviewId": 723099804,
      "rating": 7.0,
      "ratingText": "Very good",
      "reviewDate": "2023-10-03T00:00:00+07:00",
      "reviewTitle": "Good for solo travellers with a controlled budget",
      "originalTitle": "",
      "originalComment": "",
      "reviewComments": "",
      "reviewPositives": "Staff was polite and tried to help in whatever way they could.\nBathroom size was larger than expected and comfortable, if we compare it to the room size.",
      "reviewNegatives": "Internet was quite slow. \n\n Room size that I selected was small if you have one large check in luggage plus one carry-on,  as it will take up the space on ground and leave little room to walk around.",
      "reviewerCountry": "",
      "reviewGroupName": "Solo traveler",
      "roomTypeName": "",
      "lengthOfStay": 0
    },
    {
      "hotelReviewId": 1050069461,
      "rating": 10.0,
      "ratingText": "Exceptional",
      "reviewDate": "2025-11-11T10:27:00+07:00",
      "reviewTitle": "Exceptional",
      "originalTitle": "",
      "originalComment": "Harga terjangkau dengan fasilitas yg msh terjaga..sangat rekomendasi utk kamu yg mau menginap dgn hrg yg variatif dan fasilitas yg baik",
      "reviewComments": "Affordable prices with well-maintained facilities... highly recommended for those who want to stay at varied prices and with good amenities.",
      "reviewPositives": "",
      "reviewNegatives": "",
      "reviewerCountry": "Indonesia",
      "reviewGroupName": "Solo traveler",
      "roomTypeName": "Apartment",
      "lengthOfStay": 1
    },
    {
      "hotelReviewId": 917162476,
      "rating": 7.0,
      "ratingText": "Very good",
      "reviewDate": "2025-01-08T00:00:00+07:00",
      "reviewTitle": "Very good",
      "originalTitle": "",
      "originalComment": "",
      "reviewComments": "",
      "reviewPositives": "Though the room is small but it's clean and well designed.",
      "reviewNegatives": "",
      "reviewerCountry": "",
      "reviewGroupName": "Family with young children",
      "roomTypeName": "",
      "lengthOfStay": 0
    },
    {
      "hotelReviewId": 848404666,
      "rating": 10.0,
      "ratingText": "Exceptional",
      "reviewDate": "2024-08-29T01:54:00+07:00",
      "reviewTitle": "Good Value ",
      "originalTitle": "",
      "originalComment": "",
      "reviewComments": "I stayed here one night as I was catching the 1st ferry to Pulau Weh.\nThe staff are friendly and helpful.\nMy room was spacious with hot running water in the bathroom.\nIn the lobby and on all floors theirs drinking water.\nMy Home is located close to local setting places that are amazing value for money.\nThe homestay is quiet with  no traffic noise and it's clean. There is a mosque close by. The call to prayer in the morning only lasts 10 - 15 minutes. Had I not been awake I would not have heard it.\nI would stay here again.\nRemember you are in Indonesia. It is basic.",
      "reviewPositives": "",
      "reviewNegatives": "",
      "reviewerCountry": "United Kingdom",
      "reviewGroupName": "Solo traveler",
      "roomTypeName": "Apartment",
      "lengthOfStay": 1
    },
    {
      "hotelReviewId": 819659396,
      "rating": 8.0,
      "ratingText": "Excellent",
      "reviewDate": "2024-06-01T00:00:00+07:00",
      "reviewTitle": "Great Location & Great Service",
      "originalTitle": "",
      "originalComment": "",
      "reviewComments": "",
      "reviewPositives": "This is my 2nd time staying here. I prefer this place is mainly due to the location & accessibility to nearby eateries and shops",
      "reviewNegatives": "",
      "reviewerCountry": "",
      "reviewGroupName": "Group",
      "roomTypeName": "",
      "lengthOfStay": 0
    },
    {
      "hotelReviewId": 1123203686,
      "rating": 7.2,
      "ratingText": "Very good",
      "reviewDate": "2026-05-24T12:33:00+07:00",
      "reviewTitle": "Very good",
      "originalTitle": "",
      "originalComment": "",
      "reviewComments": "The first room I was given had very poor WiFi reception. But I was able to change to another one with was much better. Both rooms are on the second floor.\nThere is cold and relatively hot water dispenser on every floor.",
      "reviewPositives": "",
      "reviewNegatives": "",
      "reviewerCountry": "Hong Kong SAR, China",
      "reviewGroupName": "Solo traveler",
      "roomTypeName": "Apartment",
      "lengthOfStay": 2
    },
    {
      "hotelReviewId": 768543936,
      "rating": 5.0,
      "ratingText": "Review score",
      "reviewDate": "2024-01-20T10:21:51+07:00",
      "reviewTitle": "Unless you’re extremely broke don’t stay here spend a little extra and get a nicer place.",
      "originalTitle": "",
      "originalComment": "",
      "reviewComments": "",
      "reviewPositives": "The room was clean I guess",
      "reviewNegatives": "Very small, extremely basic, they said there was Internet but none of us could connect which was disappointing.",
      "reviewerCountry": "",
      "reviewGroupName": "Couple",
      "roomTypeName": "",
      "lengthOfStay": 0
    },
    {
      "hotelReviewId": 841476311,
      "rating": 10.0,
      "ratingText": "Exceptional",
      "reviewDate": "2024-07-31T12:56:00+07:00",
      "reviewTitle": "Best budget location to stay in Banda Aceh",
      "originalTitle": "",
      "originalComment": "",
      "reviewComments": "Located in a small complex near the city center. For the price, it’s considered very decent. Worth the stay",
      "reviewPositives": "",
      "reviewNegatives": "",
      "reviewerCountry": "Indonesia",
      "reviewGroupName": "Solo traveler",
      "roomTypeName": "Apartment",
      "lengthOfStay": 8
    },
    {
      "hotelReviewId": 735502570,
      "rating": 8.0,
      "ratingText": "Excellent",
      "reviewDate": "2023-11-03T00:00:00+07:00",
      "reviewTitle": "i will stay here in future",
      "originalTitle": "",
      "originalComment": "",
      "reviewComments": "",
      "reviewPositives": "room big and clean",
      "reviewNegatives": "nothing",
      "reviewerCountry": "",
      "reviewGroupName": "Group",
      "roomTypeName": "",
      "lengthOfStay": 0
    },
    {
      "hotelReviewId": 965161666,
      "rating": 8.0,
      "ratingText": "Excellent",
      "reviewDate": "2025-05-17T09:04:00+07:00",
      "reviewTitle": "MyHome Hotel",
      "originalTitle": "",
      "originalComment": "",
      "reviewComments": "Recommended to stay in Acheh for location assesible to nearest food & souvenir facilities ",
      "reviewPositives": "",
      "reviewNegatives": "",
      "reviewerCountry": "Malaysia",
      "reviewGroupName": "Couple",
      "roomTypeName": "Apartment",
      "lengthOfStay": 2
    },
    {
      "hotelReviewId": 723099804,
      "rating": 7.0,
      "ratingText": "Very good",
      "reviewDate": "2023-10-03T00:00:00+07:00",
      "reviewTitle": "Good for solo travellers with a controlled budget",
      "originalTitle": "",
      "originalComment": "",
      "reviewComments": "",
      "reviewPositives": "Staff was polite and tried to help in whatever way they could.\nBathroom size was larger than expected and comfortable, if we compare it to the room size.",
      "reviewNegatives": "Internet was quite slow. \n\n Room size that I selected was small if you have one large check in luggage plus one carry-on,  as it will take up the space on ground and leave little room to walk around.",
      "reviewerCountry": "",
      "reviewGroupName": "Solo traveler",
      "roomTypeName": "",
      "lengthOfStay": 0
    },
    {
      "hotelReviewId": 949673983,
      "rating": 9.2,
      "ratingText": "Exceptional",
      "reviewDate": "2025-08-15T07:23:00+07:00",
      "reviewTitle": "Exceptional",
      "originalTitle": "",
      "originalComment": "",
      "reviewComments": "Hotel bajet terbaik",
      "reviewPositives": "",
      "reviewNegatives": "",
      "reviewerCountry": "Malaysia",
      "reviewGroupName": "Couple",
      "roomTypeName": "Apartment",
      "lengthOfStay": 4
    },
    {
      "hotelReviewId": 705828917,
      "rating": 2.0,
      "ratingText": "Review score",
      "reviewDate": "2023-08-28T00:00:00+07:00",
      "reviewTitle": "Disappointing communication and did not meet agreements made",
      "originalTitle": "",
      "originalComment": "",
      "reviewComments": "",
      "reviewPositives": "",
      "reviewNegatives": "We booked this accomodation basically to store our luggages. Unfortunately our flight was cancelled and we couldn't make it to Banda aceh. The hotel agreed to not let us pay given these unforeseen circumstances, but finally they did charge us. Communication was overall very difficult.",
      "reviewerCountry": "",
      "reviewGroupName": "Family with young children",
      "roomTypeName": "",
      "lengthOfStay": 0
    },
    {
      "hotelReviewId": 733678225,
      "rating": 9.2,
      "ratingText": "Exceptional",
      "reviewDate": "2023-10-31T09:44:00+07:00",
      "reviewTitle": "Exceptional",
      "originalTitle": "",
      "originalComment": "",
      "reviewComments": "I will recommend my home if you are looking for a simple accommodation at a center of the town. ",
      "reviewPositives": "",
      "reviewNegatives": "",
      "reviewerCountry": "Indonesia",
      "reviewGroupName": "Solo traveler",
      "roomTypeName": "Apartment",
      "lengthOfStay": 2
    },
    {
      "hotelReviewId": 680819668,
      "rating": 8.0,
      "ratingText": "Excellent",
      "reviewDate": "2023-07-06T00:00:00+07:00",
      "reviewTitle": "Very good",
      "originalTitle": "",
      "originalComment": "",
      "reviewComments": "",
      "reviewPositives": "The place is clean and has an excellent location.",
      "reviewNegatives": "There is no elevator but if you travel light that should be OK or you can ask for a room on the ground floor when booking.",
      "reviewerCountry": "",
      "reviewGroupName": "Couple",
      "roomTypeName": "",
      "lengthOfStay": 0
    },
    {
      "hotelReviewId": 688611900,
      "rating": 8.0,
      "ratingText": "Excellent",
      "reviewDate": "2023-08-08T04:08:00+07:00",
      "reviewTitle": "Very good",
      "originalTitle": "",
      "originalComment": "",
      "reviewComments": "Very strategic location.\n\nWifi was so 👎",
      "reviewPositives": "",
      "reviewNegatives": "",
      "reviewerCountry": "Malaysia",
      "reviewGroupName": "Couple",
      "roomTypeName": "Apartment",
      "lengthOfStay": 1
    },
    {
      "hotelReviewId": 672921168,
      "rating": 4.0,
      "ratingText": "Review score",
      "reviewDate": "2023-06-25T16:45:16+07:00",
      "reviewTitle": "Just a overnight stay..",
      "originalTitle": "",
      "originalComment": "",
      "reviewComments": "",
      "reviewPositives": "Location quite central to shops and restaurant",
      "reviewNegatives": "Room aircond not working properly. Takes forever to cool down.",
      "reviewerCountry": "",
      "reviewGroupName": "Group",
      "roomTypeName": "",
      "lengthOfStay": 0
    },
    {
      "hotelReviewId": 606231980,
      "rating": 10.0,
      "ratingText": "Exceptional",
      "reviewDate": "2023-03-11T08:57:00+07:00",
      "reviewTitle": "its my home ",
      "originalTitle": "",
      "originalComment": "",
      "reviewComments": "feel likes home",
      "reviewPositives": "",
      "reviewNegatives": "",
      "reviewerCountry": "Indonesia",
      "reviewGroupName": "Business traveler",
      "roomTypeName": "Apartment",
      "lengthOfStay": 3
    },
    {
      "hotelReviewId": 587664584,
      "rating": 7.6,
      "ratingText": "Very good",
      "reviewDate": "2023-01-15T05:49:00+07:00",
      "reviewTitle": "Home stay hotel",
      "originalTitle": "",
      "originalComment": "",
      "reviewComments": " Recommended to budget travel. Nearby to mosque . Walking distance to food court and restoran nearby. Cimb Niagabank infront the hotel.",
      "reviewPositives": "",
      "reviewNegatives": "",
      "reviewerCountry": "Malaysia",
      "reviewGroupName": "Solo traveler",
      "roomTypeName": "Apartment",
      "lengthOfStay": 4
    },
    {
      "hotelReviewId": 267227769,
      "rating": 10.0,
      "ratingText": "Exceptional",
      "reviewDate": "2020-05-30T15:32:00+07:00",
      "reviewTitle": "Excellent ",
      "originalTitle": "",
      "originalComment": "",
      "reviewComments": "Very clean, excellent service, great location",
      "reviewPositives": "",
      "reviewNegatives": "",
      "reviewerCountry": "Indonesia",
      "reviewGroupName": "Business traveler",
      "roomTypeName": "Apartment",
      "lengthOfStay": 1
    },
    {
      "hotelReviewId": 258442325,
      "rating": 9.2,
      "ratingText": "Exceptional",
      "reviewDate": "2020-03-16T09:07:00+07:00",
      "reviewTitle": "Good place to stay",
      "originalTitle": "",
      "originalComment": "",
      "reviewComments": "Near to city center, can just walk around. Room is spacious and clean!",
      "reviewPositives": "",
      "reviewNegatives": "",
      "reviewerCountry": "Malaysia",
      "reviewGroupName": "Group",
      "roomTypeName": "Apartment",
      "lengthOfStay": 1
    },
    {
      "hotelReviewId": 244970019,
      "rating": 7.2,
      "ratingText": "Very good",
      "reviewDate": "2019-11-04T20:46:00+07:00",
      "reviewTitle": "Decent budget hotel in Banda Aceh",
      "originalTitle": "",
      "originalComment": "",
      "reviewComments": "Stayed one night at My Home Aceh. On check in the room wasn't ready which wasn't a big deal. Cleanliness of the place was okay. Staff at the hotel was helpful and tried there best to overcome the language barrier. Overall it was an okay stay.",
      "reviewPositives": "",
      "reviewNegatives": "",
      "reviewerCountry": "Germany",
      "reviewGroupName": "Couple",
      "roomTypeName": "Apartment",
      "lengthOfStay": 1
    },
    {
      "hotelReviewId": 212744660,
      "rating": 9.2,
      "ratingText": "Exceptional",
      "reviewDate": "2019-05-05T11:44:00+07:00",
      "reviewTitle": "Comfortable stay... ",
      "originalTitle": "",
      "originalComment": "",
      "reviewComments": "Very clean and easy access to all important landmarks. \n",
      "reviewPositives": "",
      "reviewNegatives": "",
      "reviewerCountry": "India",
      "reviewGroupName": "Solo traveler",
      "roomTypeName": "Apartment",
      "lengthOfStay": 1
    },
    {
      "hotelReviewId": 210683118,
      "rating": 9.2,
      "ratingText": "Exceptional",
      "reviewDate": "2019-04-01T13:48:00+07:00",
      "reviewTitle": "Good stay",
      "originalTitle": "",
      "originalComment": "",
      "reviewComments": "Clean and spacious room. The staff is helpful. Few meters away from the mainroad.\nThe water pressure is low. No lift. Only soap provided in the bathroom. \nOtherwise we had a nice stay there.",
      "reviewPositives": "",
      "reviewNegatives": "",
      "reviewerCountry": "Malaysia",
      "reviewGroupName": "Family with young children",
      "roomTypeName": "Apartment",
      "lengthOfStay": 1
    },
    {
      "hotelReviewId": 202369003,
      "rating": 7.6,
      "ratingText": "Very good",
      "reviewDate": "2019-02-17T19:04:00+07:00",
      "reviewTitle": "No Frills",
      "originalTitle": "",
      "originalComment": "",
      "reviewComments": "Located at the back of shophouses along Peunayong Street. A simple, no frills place but really serve its purpose. Clean room. Newly renovated bathroom. Comfy bed & pillow. Hot/Cold water dispenser are available in every floor. Very friendly and super helpful staff. Room was a bit small but didn’t matter for me bcoz i only be there for sleeping. There are many cafès and eateries around. Only 5 minutes walk to nearest money changer and souvenir shops. Easy to get Grab service too (if ‘MyHome’ doesn’t appear on your current location, just type ‘Seirama Coffee Shop’ - next door cafe)....the only disadvantage, no elevator. ",
      "reviewPositives": "",
      "reviewNegatives": "",
      "reviewerCountry": "Malaysia",
      "reviewGroupName": "Couple",
      "roomTypeName": "Apartment",
      "lengthOfStay": 2
    },
    {
      "hotelReviewId": 187644693,
      "rating": 8.0,
      "ratingText": "Excellent",
      "reviewDate": "2018-12-07T14:41:00+07:00",
      "reviewTitle": "Very good",
      "originalTitle": "",
      "originalComment": "",
      "reviewComments": "My Home Aceh is a very good budget hotel, well located downtown Aceh, with a kind, knowledgeable and helpful staff. I will stay with them again if I am ever in Banda Aceh and what good, clean basic accommodation.",
      "reviewPositives": "",
      "reviewNegatives": "",
      "reviewerCountry": "Canada",
      "reviewGroupName": "Solo traveler",
      "roomTypeName": "Apartment",
      "lengthOfStay": 1
    },
    {
      "hotelReviewId": 177861984,
      "rating": 8.4,
      "ratingText": "Excellent",
      "reviewDate": "2018-10-16T13:11:00+07:00",
      "reviewTitle": "Wifi",
      "originalTitle": "",
      "originalComment": "",
      "reviewComments": "The hotel should upgrade the problem of the wifi connection. Its too poor connection. Overall is okay and nice. Thanks for the warm hospitality",
      "reviewPositives": "",
      "reviewNegatives": "",
      "reviewerCountry": "Malaysia",
      "reviewGroupName": "Solo traveler",
      "roomTypeName": "Apartment",
      "lengthOfStay": 1
    },
    {
      "hotelReviewId": 176154454,
      "rating": 8.8,
      "ratingText": "Excellent",
      "reviewDate": "2018-10-08T13:52:00+07:00",
      "reviewTitle": "Good",
      "originalTitle": "",
      "originalComment": "",
      "reviewComments": "Good place to stay for travel. Near to the souvenir and food court. Nice for budget hotel. Not recommend if vacation with older because room was too small",
      "reviewPositives": "",
      "reviewNegatives": "",
      "reviewerCountry": "Malaysia",
      "reviewGroupName": "Group",
      "roomTypeName": "Apartment",
      "lengthOfStay": 3
    },
    {
      "hotelReviewId": 173864707,
      "rating": 6.0,
      "ratingText": "Good",
      "reviewDate": "2018-09-25T12:18:00+07:00",
      "reviewTitle": "Super noisy construction ",
      "originalTitle": "",
      "originalComment": "",
      "reviewComments": "The room was small but ok for the price. The bathroom was clean and modern. But I was given a room at the building where they are still doing A LOT OF construction. Imagine waking up at eight in the morning from people cutting tiles using a very loud machine in the next room. The workers also constantly banging on the wall of my room while putting nails on the wall. I don't k ow why they put me in this building. Maybe because I'm Indonesian with brown skin. If I were a white tourist I'm sure they would've given me a room in the building where there is no construction. ",
      "reviewPositives": "",
      "reviewNegatives": "",
      "reviewerCountry": "Indonesia",
      "reviewGroupName": "Solo traveler",
      "roomTypeName": "Apartment",
      "lengthOfStay": 4
    },
    {
      "hotelReviewId": 980099726,
      "rating": 8.0,
      "ratingText": "Excellent",
      "reviewDate": "2025-06-21T11:44:00+07:00",
      "reviewTitle": "Nice and quiet place ",
      "originalTitle": "",
      "originalComment": "",
      "reviewComments": "Thoroughly enjoyed the stay. Will come back in the future",
      "reviewPositives": "",
      "reviewNegatives": "",
      "reviewerCountry": "Hong Kong SAR, China",
      "reviewGroupName": "Solo traveler",
      "roomTypeName": "Apartment",
      "lengthOfStay": 1
    },
    {
      "hotelReviewId": 800583338,
      "rating": 8.0,
      "ratingText": "Excellent",
      "reviewDate": "2024-05-02T08:35:00+07:00",
      "reviewTitle": "one night stand",
      "originalTitle": "",
      "originalComment": "",
      "reviewComments": "Location is central, room is clean and spacious though no other facilities.",
      "reviewPositives": "",
      "reviewNegatives": "",
      "reviewerCountry": "Australia",
      "reviewGroupName": "Solo traveler",
      "roomTypeName": "Apartment",
      "lengthOfStay": 1
    },
    {
      "hotelReviewId": 781687483,
      "rating": 8.8,
      "ratingText": "Excellent",
      "reviewDate": "2024-03-13T09:13:00+07:00",
      "reviewTitle": "Bagus & Berbaloi.. Value for money, central location",
      "originalTitle": "",
      "originalComment": "",
      "reviewComments": "Even before our arrival, they were very responsive to text messages and helpful to queries on estimated fares from the port to the hotel. We were allowed early check in, so kind of them. Plenty of food choices in the area and coffee places. There's a water dispenser on each floor. Toilet very clean. Beds were firm and comfy. AC functioned well n strong. Great value!",
      "reviewPositives": "",
      "reviewNegatives": "",
      "reviewerCountry": "Malaysia",
      "reviewGroupName": "Couple",
      "roomTypeName": "Apartment",
      "lengthOfStay": 1
    },
    {
      "hotelReviewId": 748321496,
      "rating": 10.0,
      "ratingText": "Exceptional",
      "reviewDate": "2023-12-08T09:07:00+07:00",
      "reviewTitle": "good hotel, excellent location in Chinatown ",
      "originalTitle": "",
      "originalComment": "",
      "reviewComments": "Actually two hotels  one budget and the other a bit more upscale. Friendly staff. Good food all around",
      "reviewPositives": "",
      "reviewNegatives": "",
      "reviewerCountry": "United States",
      "reviewGroupName": "Solo traveler",
      "roomTypeName": "Apartment",
      "lengthOfStay": 16
    },
    {
      "hotelReviewId": 644602628,
      "rating": 10.0,
      "ratingText": "Exceptional",
      "reviewDate": "2023-05-01T05:22:00+07:00",
      "reviewTitle": "Best with value of money",
      "originalTitle": "",
      "originalComment": "",
      "reviewComments": "Located in center city, friendly staff, ac working very well, hot water, clean bed sheet..for me it is just excellent",
      "reviewPositives": "",
      "reviewNegatives": "",
      "reviewerCountry": "Indonesia",
      "reviewGroupName": "Family with young children",
      "roomTypeName": "Apartment",
      "lengthOfStay": 2
    },
    {
      "hotelReviewId": 633663925,
      "rating": 10.0,
      "ratingText": "Exceptional",
      "reviewDate": "2023-04-17T01:03:00+07:00",
      "reviewTitle": "Recommended",
      "originalTitle": "Recommended ",
      "originalComment": "My Home emang selalu memberikan layanan terbaik, kamar yg bersih dan Kondisi toilet yg Rapi dan baik",
      "reviewComments": "My Home really provides the best service, clean rooms, and well-maintained and tidy bathrooms.",
      "reviewPositives": "",
      "reviewNegatives": "",
      "reviewerCountry": "Indonesia",
      "reviewGroupName": "Solo traveler",
      "roomTypeName": "Apartment",
      "lengthOfStay": 1
    },
    {
      "hotelReviewId": 577935218,
      "rating": 9.6,
      "ratingText": "Exceptional",
      "reviewDate": "2022-12-15T03:33:00+07:00",
      "reviewTitle": "Convenient stay in Banda Aceh",
      "originalTitle": "",
      "originalComment": "",
      "reviewComments": "Clean room, good facilities.",
      "reviewPositives": "",
      "reviewNegatives": "",
      "reviewerCountry": "Australia",
      "reviewGroupName": "Solo traveler",
      "roomTypeName": "Apartment",
      "lengthOfStay": 1
    },
    {
      "hotelReviewId": 567751614,
      "rating": 7.2,
      "ratingText": "Very good",
      "reviewDate": "2022-11-22T08:25:00+07:00",
      "reviewTitle": "Good solid choice but misleading description ",
      "originalTitle": "",
      "originalComment": "",
      "reviewComments": "A well maintained budget hotel that was very comfortable. The only thing was that the Agoda description stated the room had a double and a single, but we got 2 single beds ( we were 3 people and it didn’t work).  I had to pay extra for another bed, though they gave me a discount for the misunderstanding. They insisted they don’t list family rooms on Agoda but it clearly stated I would be getting a double and single. It was still economical with the surcharge, though I should have received what was stated. ",
      "reviewPositives": "",
      "reviewNegatives": "",
      "reviewerCountry": "Canada",
      "reviewGroupName": "Family with young children",
      "roomTypeName": "Apartment",
      "lengthOfStay": 1
    },
    {
      "hotelReviewId": 777288284,
      "rating": 8.4,
      "ratingText": "Excellent",
      "reviewDate": "2024-03-01T06:30:00+07:00",
      "reviewTitle": "Gut für einen Zwischenstop",
      "originalTitle": "",
      "originalComment": "",
      "reviewComments": "Sehr freundliches Personal.  Es gibt viele Restaurants und Shops in der Nähe. ",
      "reviewPositives": "",
      "reviewNegatives": "",
      "reviewerCountry": "Germany",
      "reviewGroupName": "Couple",
      "roomTypeName": "Apartment",
      "lengthOfStay": 1
    },
    {
      "hotelReviewId": 766272891,
      "rating": 10.0,
      "ratingText": "Exceptional",
      "reviewDate": "2024-01-25T11:13:00+07:00",
      "reviewTitle": "Exceptional",
      "originalTitle": "",
      "originalComment": "",
      "reviewComments": "Bagus dan dekat dengan pusat kota",
      "reviewPositives": "",
      "reviewNegatives": "",
      "reviewerCountry": "Malaysia",
      "reviewGroupName": "Solo traveler",
      "roomTypeName": "Apartment",
      "lengthOfStay": 1
    },
    {
      "hotelReviewId": 257510551,
      "rating": 9.6,
      "ratingText": "Exceptional",
      "reviewDate": "2020-03-04T20:32:00+07:00",
      "reviewTitle": "Hotel yg Sgt2 berpatutan",
      "originalTitle": "",
      "originalComment": "",
      "reviewComments": "Lokasi yg Sgt dekat dgn byk kedai. \nSaya berjalan2 Di sekitar hotel sekitar pkol 11mlm dgn rasa selamat Dan tenang (3 org perempuan). \nStaff hotel pulang kan balik barang yg saya tertinggal dlm hotel dgn Keadaan selamat Dan baik\n.\nHotel ni tiada lift. Lain2 semuanya terbaik. ",
      "reviewPositives": "",
      "reviewNegatives": "",
      "reviewerCountry": "Malaysia",
      "reviewGroupName": "Group",
      "roomTypeName": "Apartment",
      "lengthOfStay": 1
    },
    {
      "hotelReviewId": 741873723,
      "rating": 10.0,
      "ratingText": "Exceptional",
      "reviewDate": "2023-11-19T08:47:00+07:00",
      "reviewTitle": "My home ,in banda Aceh ",
      "originalTitle": "",
      "originalComment": "",
      "reviewComments": "A place i call home",
      "reviewPositives": "",
      "reviewNegatives": "",
      "reviewerCountry": "Indonesia",
      "reviewGroupName": "Business traveler",
      "roomTypeName": "Apartment",
      "lengthOfStay": 2
    },
    {
      "hotelReviewId": 199077501,
      "rating": 7.6,
      "ratingText": "Very good",
      "reviewDate": "2019-01-24T08:59:00+07:00",
      "reviewTitle": "berhampiran",
      "originalTitle": "",
      "originalComment": "",
      "reviewComments": "Hotel okay, bilik besar,bersih.",
      "reviewPositives": "",
      "reviewNegatives": "",
      "reviewerCountry": "Malaysia",
      "reviewGroupName": "Family with young children",
      "roomTypeName": "Apartment",
      "lengthOfStay": 1
    }
  ]
}